bqueryd/__init__.py
bqueryd/controller.py
bqueryd/messages.py
bqueryd/node.py
bqueryd/rpc.py
bqueryd/tool.py
bqueryd/util.py
bqueryd/version.py
bqueryd/worker.py
bqueryd-0.3.10.dist-info/LICENSE
bqueryd-0.3.10.dist-info/METADATA
bqueryd-0.3.10.dist-info/WHEEL
bqueryd-0.3.10.dist-info/entry_points.txt
bqueryd-0.3.10.dist-info/top_level.txt
bqueryd-0.3.10.dist-info/zip-safe
bqueryd-0.3.10.dist-info/RECORD
