Metadata-Version: 2.1
Name: bqueryd
Version: 0.3.10
Summary: A distribution framework for Bquery
Home-page: https://github.com/visualfabriq/bqueryd
Author: Carst Vaartjes
Author-email: cvaartjes@visualfabriq.com
Maintainer: Carst Vaartjes
Maintainer-email: cvaartjes@visualfabriq.com
License: GPL2
Platform: any
Classifier: Development Status :: 4 - Beta
Classifier: Intended Audience :: Developers
Classifier: Intended Audience :: Information Technology
Classifier: Intended Audience :: Science/Research
Classifier: License :: OSI Approved :: BSD License
Classifier: Programming Language :: Python
Classifier: Topic :: Software Development :: Libraries :: Python Modules
Classifier: Operating System :: Microsoft :: Windows
Classifier: Operating System :: Unix
Classifier: Programming Language :: Python :: 2
Classifier: Programming Language :: Python :: 2.7
Classifier: Programming Language :: Python :: 3
Classifier: Programming Language :: Python :: 3.5
Classifier: Programming Language :: Python :: 3.6
Classifier: Programming Language :: Python :: 3.7
Requires-Dist: bquery (>=0.2.10)
Requires-Dist: pyzmq (>=17.1.2)
Requires-Dist: redis (>=3.0.1)
Requires-Dist: boto3 (>=1.9.82)
Requires-Dist: smart-open (>=1.9.0)
Requires-Dist: netifaces (>=0.10.9)
Requires-Dist: configobj (>=5.0.6)
Requires-Dist: psutil (>=5.0.0)
Requires-Dist: azure-storage-blob (==12.0.0)
Provides-Extra: optional
Provides-Extra: test
Requires-Dist: pandas (>=0.23.1) ; extra == 'test'
Requires-Dist: pytest (>=4.0.0) ; extra == 'test'
Requires-Dist: pytest-cov (>=2.6.0) ; extra == 'test'
Requires-Dist: codacy-coverage (>=1.3.7) ; extra == 'test'
